loginllama/__init__.py
loginllama/api.py
loginllama/loginllama.py
tests/__init__.py
tests/test_loginllama.py
loginllama-0.1.dist-info/LICENSE
loginllama-0.1.dist-info/METADATA
loginllama-0.1.dist-info/WHEEL
loginllama-0.1.dist-info/top_level.txt
loginllama-0.1.dist-info/RECORD
