Metadata-Version: 2.1
Name: loginllama
Version: 0.1
Summary: LoginLlama Python SDK for detecting suspicious logins
Home-page: https://github.com/joshghent/loginllama.py
Author: Josh Ghent
Author-email: me@joshghent.com
Classifier: Programming Language :: Python :: 3
Classifier: Operating System :: OS Independent
Requires-Python: >=3.6
License-File: LICENSE
Requires-Dist: requests
